MANIFEST.in
README.rst
setup.py
contrib/debian-release.sh
contrib/rpm-release.py
contrib/tldp.spec
contrib/tldp.spec.in
docs/conf.py
docs/ldptool-man.rst
docs/ldptool.1
etc/ldptool.ini
tldp/__init__.py
tldp/cascadingconfig.py
tldp/config.py
tldp/driver.py
tldp/inventory.py
tldp/ldpcollection.py
tldp/outputs.py
tldp/sources.py
tldp/typeguesser.py
tldp/utils.py
tldp.egg-info/PKG-INFO
tldp.egg-info/SOURCES.txt
tldp.egg-info/dependency_links.txt
tldp.egg-info/entry_points.txt
tldp.egg-info/requires.txt
tldp.egg-info/top_level.txt
tldp/doctypes/__init__.py
tldp/doctypes/asciidoc.py
tldp/doctypes/common.py
tldp/doctypes/docbook4xml.py
tldp/doctypes/docbook5xml.py
tldp/doctypes/docbooksgml.py
tldp/doctypes/example.py
tldp/doctypes/linuxdoc.py
tldp/doctypes/markdown.py
tldp/doctypes/rst.py