Metadata-Version: 1.1
Name: tldp
Version: 0.7.13
Summary: automatic publishing tool for DocBook, Linuxdoc and Asciidoc
Home-page: http://en.tldp.org/
Author: Martin A. Brown
Author-email: martin@linux-ip.net
License: MIT
Platform: UNKNOWN
Classifier: Development Status :: 4 - Beta
Classifier: Intended Audience :: Developers
Classifier: License :: OSI Approved :: MIT License
Classifier: Operating System :: OS Independent
Classifier: Programming Language :: Python
Classifier: Topic :: Software Development :: Documentation
Classifier: Topic :: Software Development :: Libraries :: Python Modules
